[
  {
    "title": "Dune",
    "genre": "sci-fi",
    "year": 2021,
    "rating": 9.9,
    "review": ""
  },
  {
    "title": "I origins",
    "genre": "drama",
    "year": 2014,
    "rating": 0.0,
    "review": ""
  },
  {
    "title": "Memento",
    "genre": "thriller",
    "year": 2000,
    "rating": 3.0,
    "review": "The plot is centred around a man who is seeking vengeance for his dead wife but there is a problem: he is unable to form new memories and he forgets everything he discovers."
  },
  {
    "title": "Inception",
    "genre": "action",
    "year": 2010,
    "rating": 0.0,
    "review": ""
  },
  {
    "title": "Memento",
    "genre": "thriller",
    "year": 2000,
    "rating": 0.0,
    "review": ""
  }
]